{"box_data": [{"position": {"minX": 315.25, "minY": 321.25, "maxX": 344.25, "maxY": 338.75}, "class_id": 0, "box_caption": "fire 0.324", "scores": {"class_score": 0.324462890625}, "domain": "pixel"}, {"position": {"minX": 319.0, "minY": 317.25, "maxX": 346.5, "maxY": 336.75}, "class_id": 0, "box_caption": "fire 0.299", "scores": {"class_score": 0.299072265625}, "domain": "pixel"}, {"position": {"minX": 314.5, "minY": 315.5, "maxX": 350.0, "maxY": 344.0}, "class_id": 0, "box_caption": "fire 0.052", "scores": {"class_score": 0.05242919921875}, "domain": "pixel"}, {"position": {"minX": 309.5, "minY": 323.5, "maxX": 334.5, "maxY": 340.5}, "class_id": 0, "box_caption": "fire 0.051", "scores": {"class_score": 0.051177978515625}, "domain": "pixel"}, {"position": {"minX": -1.9921875, "minY": 4.46875, "maxX": 25.78125, "maxY": 108.625}, "class_id": 1, "box_caption": "smoke 0.018", "scores": {"class_score": 0.018096923828125}, "domain": "pixel"}, {"position": {"minX": 314.75, "minY": 311.75, "maxX": 344.75, "maxY": 336.25}, "class_id": 1, "box_caption": "smoke 0.016", "scores": {"class_score": 0.01629638671875}, "domain": "pixel"}, {"position": {"minX": -4.125, "minY": 16.375, "maxX": 35.625, "maxY": 121.5}, "class_id": 1, "box_caption": "smoke 0.010", "scores": {"class_score": 0.0096893310546875}, "domain": "pixel"}, {"position": {"minX": 384.75, "minY": 14.6015625, "maxX": 402.25, "maxY": 26.75}, "class_id": 0, "box_caption": "fire 0.009", "scores": {"class_score": 0.0091552734375}, "domain": "pixel"}, {"position": {"minX": 311.75, "minY": 325.5, "maxX": 344.25, "maxY": 355.0}, "class_id": 0, "box_caption": "fire 0.009", "scores": {"class_score": 0.00914764404296875}, "domain": "pixel"}, {"position": {"minX": 52.625, "minY": 333.75, "maxX": 83.875, "maxY": 364.25}, "class_id": 1, "box_caption": "smoke 0.009", "scores": {"class_score": 0.0089111328125}, "domain": "pixel"}, {"position": {"minX": 320.25, "minY": 309.5, "maxX": 345.25, "maxY": 331.0}, "class_id": 0, "box_caption": "fire 0.007", "scores": {"class_score": 0.00732421875}, "domain": "pixel"}, {"position": {"minX": -1.4609375, "minY": 30.53125, "maxX": 25.375, "maxY": 141.875}, "class_id": 1, "box_caption": "smoke 0.007", "scores": {"class_score": 0.00727081298828125}, "domain": "pixel"}, {"position": {"minX": -3.8828125, "minY": -4.1875, "maxX": 34.9375, "maxY": 91.0}, "class_id": 1, "box_caption": "smoke 0.007", "scores": {"class_score": 0.00724029541015625}, "domain": "pixel"}, {"position": {"minX": 311.75, "minY": 302.0, "maxX": 347.25, "maxY": 337.5}, "class_id": 0, "box_caption": "fire 0.005", "scores": {"class_score": 0.00534820556640625}, "domain": "pixel"}, {"position": {"minX": 311.75, "minY": 302.0, "maxX": 347.25, "maxY": 337.5}, "class_id": 1, "box_caption": "smoke 0.005", "scores": {"class_score": 0.0049591064453125}, "domain": "pixel"}, {"position": {"minX": 320.25, "minY": 309.5, "maxX": 345.25, "maxY": 331.0}, "class_id": 1, "box_caption": "smoke 0.005", "scores": {"class_score": 0.004894256591796875}, "domain": "pixel"}, {"position": {"minX": 314.75, "minY": 320.25, "maxX": 343.75, "maxY": 339.75}, "class_id": 1, "box_caption": "smoke 0.005", "scores": {"class_score": 0.0048675537109375}, "domain": "pixel"}, {"position": {"minX": -0.890625, "minY": 2.34375, "maxX": 23.421875, "maxY": 74.625}, "class_id": 1, "box_caption": "smoke 0.005", "scores": {"class_score": 0.00482177734375}, "domain": "pixel"}, {"position": {"minX": 0.3828125, "minY": 305.0, "maxX": 18.15625, "maxY": 382.5}, "class_id": 1, "box_caption": "smoke 0.004", "scores": {"class_score": 0.0044708251953125}, "domain": "pixel"}, {"position": {"minX": -7.65625, "minY": 23.46875, "maxX": 44.5, "maxY": 99.375}, "class_id": 1, "box_caption": "smoke 0.004", "scores": {"class_score": 0.00412750244140625}, "domain": "pixel"}, {"position": {"minX": 307.75, "minY": 292.75, "maxX": 357.25, "maxY": 352.75}, "class_id": 0, "box_caption": "fire 0.004", "scores": {"class_score": 0.0038928985595703125}, "domain": "pixel"}, {"position": {"minX": 60.5625, "minY": 336.25, "maxX": 86.3125, "maxY": 361.25}, "class_id": 1, "box_caption": "smoke 0.004", "scores": {"class_score": 0.0038852691650390625}, "domain": "pixel"}, {"position": {"minX": 302.25, "minY": 324.25, "maxX": 327.25, "maxY": 338.25}, "class_id": 0, "box_caption": "fire 0.004", "scores": {"class_score": 0.0036773681640625}, "domain": "pixel"}, {"position": {"minX": 542.0, "minY": 46.0, "maxX": 589.0, "maxY": 98.625}, "class_id": 1, "box_caption": "smoke 0.004", "scores": {"class_score": 0.0036563873291015625}, "domain": "pixel"}, {"position": {"minX": 313.0, "minY": 308.25, "maxX": 341.0, "maxY": 329.75}, "class_id": 1, "box_caption": "smoke 0.003", "scores": {"class_score": 0.0034332275390625}, "domain": "pixel"}, {"position": {"minX": -0.5390625, "minY": 331.0, "maxX": 17.4375, "maxY": 386.0}, "class_id": 1, "box_caption": "smoke 0.003", "scores": {"class_score": 0.0033416748046875}, "domain": "pixel"}, {"position": {"minX": 320.75, "minY": 299.25, "maxX": 342.25, "maxY": 322.75}, "class_id": 1, "box_caption": "smoke 0.003", "scores": {"class_score": 0.0033283233642578125}, "domain": "pixel"}, {"position": {"minX": 321.75, "minY": 303.0, "maxX": 351.75, "maxY": 330.5}, "class_id": 1, "box_caption": "smoke 0.003", "scores": {"class_score": 0.0032958984375}, "domain": "pixel"}, {"position": {"minX": -3.671875, "minY": 45.53125, "maxX": 36.0625, "maxY": 156.25}, "class_id": 1, "box_caption": "smoke 0.003", "scores": {"class_score": 0.0031528472900390625}, "domain": "pixel"}, {"position": {"minX": 385.75, "minY": 18.5625, "maxX": 403.25, "maxY": 30.8125}, "class_id": 0, "box_caption": "fire 0.003", "scores": {"class_score": 0.0031108856201171875}, "domain": "pixel"}, {"position": {"minX": 314.5, "minY": 315.5, "maxX": 350.0, "maxY": 344.0}, "class_id": 1, "box_caption": "smoke 0.003", "scores": {"class_score": 0.003093719482421875}, "domain": "pixel"}, {"position": {"minX": 380.0, "minY": 13.6484375, "maxX": 400.0, "maxY": 25.59375}, "class_id": 0, "box_caption": "fire 0.003", "scores": {"class_score": 0.0030460357666015625}, "domain": "pixel"}, {"position": {"minX": -1.9375, "minY": 53.375, "maxX": 26.0625, "maxY": 182.125}, "class_id": 1, "box_caption": "smoke 0.003", "scores": {"class_score": 0.00304412841796875}, "domain": "pixel"}, {"position": {"minX": 661.5, "minY": 263.25, "maxX": 673.5, "maxY": 363.75}, "class_id": 1, "box_caption": "smoke 0.003", "scores": {"class_score": 0.0028285980224609375}, "domain": "pixel"}, {"position": {"minX": 319.75, "minY": 318.0, "maxX": 346.25, "maxY": 335.5}, "class_id": 1, "box_caption": "smoke 0.003", "scores": {"class_score": 0.0027313232421875}, "domain": "pixel"}, {"position": {"minX": 303.0, "minY": 277.5, "maxX": 358.5, "maxY": 346.0}, "class_id": 1, "box_caption": "smoke 0.003", "scores": {"class_score": 0.0027217864990234375}, "domain": "pixel"}, {"position": {"minX": 296.25, "minY": 301.25, "maxX": 341.25, "maxY": 334.25}, "class_id": 1, "box_caption": "smoke 0.003", "scores": {"class_score": 0.002716064453125}, "domain": "pixel"}, {"position": {"minX": 57.8125, "minY": 328.25, "maxX": 91.4375, "maxY": 363.75}, "class_id": 1, "box_caption": "smoke 0.003", "scores": {"class_score": 0.0026683807373046875}, "domain": "pixel"}, {"position": {"minX": 327.0, "minY": 297.5, "maxX": 347.5, "maxY": 322.0}, "class_id": 1, "box_caption": "smoke 0.003", "scores": {"class_score": 0.002620697021484375}, "domain": "pixel"}, {"position": {"minX": 660.0, "minY": 220.0, "maxX": 673.0, "maxY": 317.0}, "class_id": 1, "box_caption": "smoke 0.003", "scores": {"class_score": 0.002582550048828125}, "domain": "pixel"}, {"position": {"minX": 313.0, "minY": 299.5, "maxX": 336.0, "maxY": 322.0}, "class_id": 1, "box_caption": "smoke 0.002", "scores": {"class_score": 0.0024280548095703125}, "domain": "pixel"}, {"position": {"minX": 656.0, "minY": 247.5, "maxX": 673.0, "maxY": 348.0}, "class_id": 1, "box_caption": "smoke 0.002", "scores": {"class_score": 0.00240325927734375}, "domain": "pixel"}, {"position": {"minX": -1.15625, "minY": 279.75, "maxX": 23.0625, "maxY": 380.25}, "class_id": 1, "box_caption": "smoke 0.002", "scores": {"class_score": 0.0023651123046875}, "domain": "pixel"}, {"position": {"minX": 321.75, "minY": 303.0, "maxX": 351.75, "maxY": 330.5}, "class_id": 0, "box_caption": "fire 0.002", "scores": {"class_score": 0.0023593902587890625}, "domain": "pixel"}, {"position": {"minX": 420.75, "minY": 14.328125, "maxX": 442.25, "maxY": 27.421875}, "class_id": 0, "box_caption": "fire 0.002", "scores": {"class_score": 0.0023326873779296875}, "domain": "pixel"}, {"position": {"minX": 2.6015625, "minY": 109.75, "maxX": 17.5625, "maxY": 221.0}, "class_id": 1, "box_caption": "smoke 0.002", "scores": {"class_score": 0.002262115478515625}, "domain": "pixel"}, {"position": {"minX": -2.0234375, "minY": 355.75, "maxX": 19.0625, "maxY": 384.25}, "class_id": 1, "box_caption": "smoke 0.002", "scores": {"class_score": 0.002239227294921875}, "domain": "pixel"}, {"position": {"minX": 329.5, "minY": 321.25, "maxX": 353.5, "maxY": 339.75}, "class_id": 0, "box_caption": "fire 0.002", "scores": {"class_score": 0.002185821533203125}, "domain": "pixel"}, {"position": {"minX": 426.25, "minY": 11.9609375, "maxX": 444.25, "maxY": 24.90625}, "class_id": 0, "box_caption": "fire 0.002", "scores": {"class_score": 0.0021648406982421875}, "domain": "pixel"}, {"position": {"minX": 323.5, "minY": 313.5, "maxX": 356.0, "maxY": 339.5}, "class_id": 0, "box_caption": "fire 0.002", "scores": {"class_score": 0.0021514892578125}, "domain": "pixel"}, {"position": {"minX": 310.5, "minY": 290.75, "maxX": 345.0, "maxY": 318.75}, "class_id": 1, "box_caption": "smoke 0.002", "scores": {"class_score": 0.00212860107421875}, "domain": "pixel"}, {"position": {"minX": 186.75, "minY": 181.875, "maxX": 484.25, "maxY": 483.5}, "class_id": 0, "box_caption": "fire 0.002", "scores": {"class_score": 0.0021266937255859375}, "domain": "pixel"}, {"position": {"minX": 0.609375, "minY": 263.0, "maxX": 17.828125, "maxY": 366.0}, "class_id": 1, "box_caption": "smoke 0.002", "scores": {"class_score": 0.0021266937255859375}, "domain": "pixel"}, {"position": {"minX": 0.9140625, "minY": 114.0, "maxX": 21.28125, "maxY": 255.5}, "class_id": 1, "box_caption": "smoke 0.002", "scores": {"class_score": 0.002109527587890625}, "domain": "pixel"}, {"position": {"minX": -1.28125, "minY": 110.75, "maxX": 32.15625, "maxY": 213.25}, "class_id": 1, "box_caption": "smoke 0.002", "scores": {"class_score": 0.0020999908447265625}, "domain": "pixel"}, {"position": {"minX": 656.0, "minY": 204.125, "maxX": 672.0, "maxY": 300.0}, "class_id": 1, "box_caption": "smoke 0.002", "scores": {"class_score": 0.0020885467529296875}, "domain": "pixel"}, {"position": {"minX": -1.4921875, "minY": 8.6875, "maxX": 17.03125, "maxY": 94.9375}, "class_id": 1, "box_caption": "smoke 0.002", "scores": {"class_score": 0.0020313262939453125}, "domain": "pixel"}, {"position": {"minX": -5.34375, "minY": 72.875, "maxX": 38.28125, "maxY": 189.875}, "class_id": 1, "box_caption": "smoke 0.002", "scores": {"class_score": 0.001964569091796875}, "domain": "pixel"}, {"position": {"minX": 653.0, "minY": 148.25, "maxX": 672.0, "maxY": 257.25}, "class_id": 1, "box_caption": "smoke 0.002", "scores": {"class_score": 0.0018291473388671875}, "domain": "pixel"}, {"position": {"minX": 652.5, "minY": 219.75, "maxX": 672.5, "maxY": 314.25}, "class_id": 1, "box_caption": "smoke 0.002", "scores": {"class_score": 0.001617431640625}, "domain": "pixel"}, {"position": {"minX": -2.84375, "minY": 339.5, "maxX": 13.65625, "maxY": 389.5}, "class_id": 1, "box_caption": "smoke 0.002", "scores": {"class_score": 0.0016117095947265625}, "domain": "pixel"}, {"position": {"minX": 425.25, "minY": 8.7421875, "maxX": 452.75, "maxY": 29.125}, "class_id": 0, "box_caption": "fire 0.002", "scores": {"class_score": 0.001583099365234375}, "domain": "pixel"}, {"position": {"minX": 331.0, "minY": 315.5, "maxX": 351.0, "maxY": 336.0}, "class_id": 0, "box_caption": "fire 0.002", "scores": {"class_score": 0.001529693603515625}, "domain": "pixel"}, {"position": {"minX": 326.75, "minY": 290.0, "maxX": 354.75, "maxY": 318.0}, "class_id": 1, "box_caption": "smoke 0.002", "scores": {"class_score": 0.0015172958374023438}, "domain": "pixel"}, {"position": {"minX": 1.0078125, "minY": 93.4375, "maxX": 20.15625, "maxY": 202.75}, "class_id": 1, "box_caption": "smoke 0.002", "scores": {"class_score": 0.0015020370483398438}, "domain": "pixel"}, {"position": {"minX": 0.03125, "minY": -7.109375, "maxX": 13.828125, "maxY": 64.5}, "class_id": 1, "box_caption": "smoke 0.001", "scores": {"class_score": 0.0014896392822265625}, "domain": "pixel"}, {"position": {"minX": 659.5, "minY": 186.125, "maxX": 672.5, "maxY": 287.25}, "class_id": 1, "box_caption": "smoke 0.001", "scores": {"class_score": 0.0014715194702148438}, "domain": "pixel"}, {"position": {"minX": 389.75, "minY": 14.484375, "maxX": 410.25, "maxY": 27.609375}, "class_id": 0, "box_caption": "fire 0.001", "scores": {"class_score": 0.0014667510986328125}, "domain": "pixel"}, {"position": {"minX": 191.875, "minY": 215.75, "maxX": 298.75, "maxY": 302.75}, "class_id": 1, "box_caption": "smoke 0.001", "scores": {"class_score": 0.0014543533325195312}, "domain": "pixel"}, {"position": {"minX": 649.5, "minY": 118.375, "maxX": 671.5, "maxY": 224.375}, "class_id": 1, "box_caption": "smoke 0.001", "scores": {"class_score": 0.0013723373413085938}, "domain": "pixel"}, {"position": {"minX": -0.921875, "minY": -0.109375, "maxX": 33.125, "maxY": 60.4375}, "class_id": 1, "box_caption": "smoke 0.001", "scores": {"class_score": 0.0013713836669921875}, "domain": "pixel"}, {"position": {"minX": 0.09375, "minY": -6.890625, "maxX": 21.296875, "maxY": 51.5}, "class_id": 1, "box_caption": "smoke 0.001", "scores": {"class_score": 0.0013208389282226562}, "domain": "pixel"}, {"position": {"minX": 396.25, "minY": 310.5, "maxX": 422.75, "maxY": 339.5}, "class_id": 1, "box_caption": "smoke 0.001", "scores": {"class_score": 0.001255035400390625}, "domain": "pixel"}, {"position": {"minX": 307.0, "minY": 283.5, "maxX": 347.5, "maxY": 323.5}, "class_id": 1, "box_caption": "smoke 0.001", "scores": {"class_score": 0.0012149810791015625}, "domain": "pixel"}, {"position": {"minX": 1.2109375, "minY": 207.5, "maxX": 17.46875, "maxY": 327.0}, "class_id": 1, "box_caption": "smoke 0.001", "scores": {"class_score": 0.0012111663818359375}, "domain": "pixel"}, {"position": {"minX": -1.984375, "minY": 238.5, "maxX": 23.546875, "maxY": 356.0}, "class_id": 1, "box_caption": "smoke 0.001", "scores": {"class_score": 0.0011987686157226562}, "domain": "pixel"}, {"position": {"minX": -8.265625, "minY": 46.90625, "maxX": 44.5625, "maxY": 123.0}, "class_id": 1, "box_caption": "smoke 0.001", "scores": {"class_score": 0.0011310577392578125}, "domain": "pixel"}, {"position": {"minX": 313.0, "minY": 308.25, "maxX": 341.0, "maxY": 329.75}, "class_id": 0, "box_caption": "fire 0.001", "scores": {"class_score": 0.0011129379272460938}, "domain": "pixel"}, {"position": {"minX": 540.5, "minY": 53.78125, "maxX": 577.5, "maxY": 107.25}, "class_id": 1, "box_caption": "smoke 0.001", "scores": {"class_score": 0.0010709762573242188}, "domain": "pixel"}, {"position": {"minX": 163.25, "minY": 211.375, "maxX": 272.75, "maxY": 286.0}, "class_id": 1, "box_caption": "smoke 0.001", "scores": {"class_score": 0.0010633468627929688}, "domain": "pixel"}, {"position": {"minX": 63.375, "minY": 322.0, "maxX": 105.625, "maxY": 363.5}, "class_id": 1, "box_caption": "smoke 0.001", "scores": {"class_score": 0.0010557174682617188}, "domain": "pixel"}, {"position": {"minX": 305.0, "minY": 307.5, "maxX": 333.0, "maxY": 328.0}, "class_id": 1, "box_caption": "smoke 0.001", "scores": {"class_score": 0.0010538101196289062}, "domain": "pixel"}, {"position": {"minX": 659.0, "minY": 301.0, "maxX": 674.0, "maxY": 387.5}, "class_id": 1, "box_caption": "smoke 0.001", "scores": {"class_score": 0.0010318756103515625}, "domain": "pixel"}, {"position": {"minX": 391.0, "minY": 20.03125, "maxX": 412.5, "maxY": 31.3125}, "class_id": 0, "box_caption": "fire 0.001", "scores": {"class_score": 0.0010042190551757812}, "domain": "pixel"}], "class_labels": {"0": "fire", "1": "smoke"}}